processor.v
module processor (
    input wire clk,
    input wire rst,
    input wire DMA_req,         // DMA Request signal to Outside
    output reg drq,             // DMA Request Signal From CPU to controller
    input wire hrq,             // Hold Request Signal from DMA to CPU
    output reg start_transfer,  // Hold Acknowledgement Signal/Start Transferring Signal from CPU
    input wire dack,            // DMA Acknowledgement Signal
    input wire transfer_done   // Transfer Completion Signal
);

reg [1:0] state;
parameter NORMAL = 2'b00, HOLD_REQ = 2'b01, HOLD = 2'b10;


always @(posedge clk ) begin
    if(rst) begin
        drq <= 0;
        start_transfer <=0;
        state <= NORMAL;
    end
    else begin
        case (state)
            // The CPU is normal computation State occupying the Memory buses
            NORMAL: begin
                if(DMA_req == 1'b1 && transfer_done == 1'b0) begin
                    // If CPU gets any external DMA request signal, then it send drq signal to DMA
                    drq <= 1'b1;
                    state <= HOLD_REQ;
                end 
                else begin
                    drq <= 1'b0;
                    state <= NORMAL;
                end
            end 

            HOLD_REQ: begin
                if(hrq == 1'b1) begin
                    // When CPU gets Hold Request signal from DMA, it transitions to HOLD state, by releasing the memory buses.
                    // And Provides Hold Acknowledgement Signal.
                    start_transfer <= 1'b1;
                    state <= HOLD;
                end
            end

            HOLD: begin
                // Till when the transfer is going on, CPU will be in HOLD State without any memory operations.
                // and will wait for Transfer done signal
                if(dack == 1'b1 && transfer_done == 1'b0) begin
                    state <= HOLD;
                end
                else if(transfer_done == 1'b1)
                    // if the transfer is done, then it will go to NORMAL State.
                    state <= NORMAL;
            end

            default: state <= NORMAL;
        endcase
    end
end
    
endmodule

qdma_block_transfer.v
module qdma_block_transfer (
    input wire clk,                            
    input wire rst,                            
    input wire drq,                // DMA Request signal for data transferring from CPU
    output reg hrq,                // Hold Request Signal fed to CPU
    input wire start_transfer,     // Hold Acknowledgement Signal from signal enabling transfer from CPU
    output reg dack,               // DMA Acknowledgement Signal
    input [1:0] transfer_type,     // Transfer type: 2'b00 for memory-to-memory, 2'b01 for peripheral-to-memory
    input [2:0] src_module,        // Select Source Module
    input [2:0] dest_module,       // Select Destination Module
    input [4:0] src_address,       // Select Source Address
    input [4:0] dest_address,      // Select Destination Address
    input [4:0] words,             // Number od words to be transferred 
    output reg transfer_done       // Transfer Completion Signal to CPU
);

// Internal memory
reg [7:0] memory0 [0:31];
reg [7:0] memory1 [0:31];
reg [7:0] memory2 [0:31];
reg [7:0] memory3 [0:31];
reg [7:0] memory4 [0:31];
reg [7:0] memory5 [0:31];
reg [7:0] memory6 [0:31];
reg [7:0] memory7 [0:31];

// Peripheral Buffers
reg [7:0] peripheral0 [0:31];
reg [7:0] peripheral1 [0:31];
reg [7:0] peripheral2 [0:31];
reg [7:0] peripheral3 [0:31];
reg [7:0] peripheral4 [0:31];
reg [7:0] peripheral5 [0:31];
reg [7:0] peripheral6 [0:31];
reg [7:0] peripheral7 [0:31];

// Parameters for data rate management
parameter DELAY_CYCLES = 2;   // Delay cycles between transfers
parameter FIFO_DEPTH = 8;     // Depth of FIFO buffer

// Circular FIFO buffer
reg [7:0] fifo [0:FIFO_DEPTH-1];
reg [3:0] fifo_wr_ptr, fifo_rd_ptr;
reg [3:0] fifo_count;

// Internal signals
reg [4:0] src_addr, dest_addr;          // Source and destination memory addresses
reg [4:0] words_to_be_transferred;      // Number of words to be transferred
reg [2:0] state;                        // State machine state
reg [1:0] delay_cycles_counter;         // Counter for delay cycles

// Define state machine states
parameter DMA_REQ = 3'b000, IDLE = 3'b001, READ = 3'b010, TRANSFER = 3'b011, DELAY = 3'b100, DONE = 3'b101;

// Initialize internal memory and signals
initial begin
    // Initialize FIFO buffer pointers and count
    fifo_wr_ptr = 0;
    fifo_rd_ptr = 0;
    fifo_count = 0;

    // Initialize other signals
    src_addr = 0;
    dest_addr = 0;
    state = DMA_REQ;
    delay_cycles_counter = 0;
    transfer_done = 0;
end

// State machine for data transfer and delay management
always @(posedge clk) begin
    if (rst) begin
        // Reset state machine and internal signals
        state <= DMA_REQ;
        src_addr <= 0;
        dest_addr <= 0;
        delay_cycles_counter <= 0;
        fifo_wr_ptr <= 0;
        fifo_rd_ptr <= 0;
        fifo_count <= 0;
        transfer_done <= 0;
        words_to_be_transferred <= 0;
    end else begin
        // State machine transitions
        case(state)
            DMA_REQ: begin
                // Check for DMA Request Signal
                if (drq == 1'b1) begin
                        // Send Hold Request Signal to CPU
                        hrq <= 1'b1;
                        state <= IDLE;
                    end
                else begin
                    hrq <= 1'b0;
                end
            end

            IDLE: begin
                // Check for transfer request/Hold Acknowledgement Signal
                if (start_transfer) begin
                    // Send DMA Acknowledgement Signal
                    dack <= 1'b1;
                    src_addr <= src_address;
                    dest_addr <= dest_address;
                    words_to_be_transferred <= words;
                    state <= READ;
                end
                else begin
                    dack <= 1'b0;
                end
            end

            READ: begin
                if(dack == 1'b1 && words_to_be_transferred > 0) begin
                    if (transfer_type == 2'b00) begin
                        // Write data to FIFO buffer if it's a memory-to-memory transfer
                        case (src_module)
                            3'b000 : fifo[fifo_wr_ptr] <= memory0[src_addr]; 
                            3'b001 : fifo[fifo_wr_ptr] <= memory1[src_addr]; 
                            3'b010 : fifo[fifo_wr_ptr] <= memory2[src_addr]; 
                            3'b011 : fifo[fifo_wr_ptr] <= memory3[src_addr]; 
                            3'b100 : fifo[fifo_wr_ptr] <= memory4[src_addr]; 
                            3'b101 : fifo[fifo_wr_ptr] <= memory5[src_addr]; 
                            3'b110 : fifo[fifo_wr_ptr] <= memory6[src_addr]; 
                            3'b111 : fifo[fifo_wr_ptr] <= memory7[src_addr]; 
                        endcase
                    end else begin
                        // Write data to FIFO buffer if it's a peripheral-to-memory transfer
                        case (src_module)
                            3'b000 : fifo[fifo_wr_ptr] <= peripheral0[src_addr]; 
                            3'b001 : fifo[fifo_wr_ptr] <= peripheral1[src_addr]; 
                            3'b010 : fifo[fifo_wr_ptr] <= peripheral2[src_addr]; 
                            3'b011 : fifo[fifo_wr_ptr] <= peripheral3[src_addr]; 
                            3'b100 : fifo[fifo_wr_ptr] <= peripheral4[src_addr]; 
                            3'b101 : fifo[fifo_wr_ptr] <= peripheral5[src_addr]; 
                            3'b110 : fifo[fifo_wr_ptr] <= peripheral6[src_addr]; 
                            3'b111 : fifo[fifo_wr_ptr] <= peripheral7[src_addr]; 
                        endcase
                    end
                    if (fifo_wr_ptr == FIFO_DEPTH - 1)   // Circular FIFO
                        fifo_wr_ptr <= 0;            // reset the write pointer
                    else
                        fifo_wr_ptr <= fifo_wr_ptr + 1; // Incrementing Write Pointer

                    fifo_count <= fifo_count + 1;   // Incrementing FIFO Count
                    // Move to transfer state
                    state <= TRANSFER;
                end
            end
            TRANSFER: begin
                // Perform data transfer from FIFO buffer
                if (fifo_count > 0) begin
                    // Read data from FIFO buffer
                    // Write data to Destination from FIFO buffer if it's a memory-to-memory transfer/peripheral-to-meory transfer
                        case (dest_module)
                            3'b000 : memory0[dest_addr] <= fifo[fifo_rd_ptr]; 
                            3'b001 : memory1[dest_addr] <= fifo[fifo_rd_ptr]; 
                            3'b010 : memory2[dest_addr] <= fifo[fifo_rd_ptr];
                            3'b011 : memory3[dest_addr] <= fifo[fifo_rd_ptr]; 
                            3'b100 : memory4[dest_addr] <= fifo[fifo_rd_ptr]; 
                            3'b101 : memory5[dest_addr] <= fifo[fifo_rd_ptr]; 
                            3'b110 : memory6[dest_addr] <= fifo[fifo_rd_ptr]; 
                            3'b111 : memory7[dest_addr] <= fifo[fifo_rd_ptr]; 
                        endcase

                    if (fifo_rd_ptr == FIFO_DEPTH - 1)    // Circular FIFO
                        fifo_rd_ptr <= 0;                // reseting the read pointer
                    else 
                        fifo_rd_ptr <= fifo_rd_ptr + 1;  // Incrementing Read Pointer

                    fifo_count <= fifo_count - 1;    // Decrementing FIFO Count
                    // Increment memory addresses
                    src_addr <= src_addr + 1;
                    dest_addr <= dest_addr + 1;

                    words_to_be_transferred <= words_to_be_transferred - 1; // Decrement the Count of words need to be transferred
                    // Move to delay state
                    state <= DELAY;
                end else begin
                    // Return to idle state if no data in FIFO buffer
                    state <= IDLE;
                end
            end
            DELAY: begin
                // Perform delay
                if (delay_cycles_counter < DELAY_CYCLES) begin
                    // Increment delay counter
                    delay_cycles_counter <= delay_cycles_counter + 1;
                    state <= DELAY;
                end
                else if (words_to_be_transferred > 0) begin
                    delay_cycles_counter <= 0;
                    state <= READ;
                end
                 else begin
                    // Reset delay counter and transition to DONE state
                    delay_cycles_counter <= 0;
                    state <= DONE;
                end
            end
            DONE: begin
                // Enable the Transfer done signal
                transfer_done <= 1'b1;
                state <= DONE;
            end
            default: state <= DMA_REQ;
        endcase
    end
end


endmodule

qdma_block_transfer_tb.v
`timescale 1ns / 1ps

`include "qdma_block_transfer.v"
`include "processor.v"
module testbench;

    // Parameters
    parameter CLK_PERIOD = 10; // Clock period in ns

    // Signals
    reg clk;
    reg rst;
    reg DMA_req;
    reg [4:0] words;
    wire drq;
    wire hrq;
    wire start_transfer;
    wire dack;
    wire transfer_done;
    reg [1:0] transfer_type;
    reg [2:0] src_module;
    reg [2:0] dest_module;
    reg [4:0] src_address;
    reg [4:0] dest_address;
    
    integer i;
    // Instantiate modules
    qdma_block_transfer uut (
        .clk(clk),
        .rst(rst),
        .drq(drq),
        .hrq(hrq),
        .start_transfer(start_transfer),
        .dack(dack),
        .transfer_type(transfer_type),
        .src_module(src_module),
        .dest_module(dest_module),
        .src_address(src_address),
        .dest_address(dest_address),
        .words(words),
        .transfer_done(transfer_done)
    );

    processor cpu (
        .clk(clk),
        .rst(rst),
        .DMA_req(DMA_req),
        .drq(drq),
        .hrq(hrq),
        .start_transfer(start_transfer),
        .dack(dack),
        .transfer_done(transfer_done)
    );

    // Clock generation
    always #CLK_PERIOD clk = ~clk;

    // Initializations
    initial
        begin
            $display("Writing to Peripheral-1 Module");
            for (i=0 ; i<15 ; i=i+1)
                uut.peripheral1[i+10] = i + 10;
            $display("Done Loading into Peripheral-1 Module");
        end


    initial begin

        $dumpfile("test.vcd");
        $dumpvars(0,testbench);
        
        clk = 0; // Initialize clock
        rst = 1; // Reset

        #20;
        rst = 0; // Release reset

        transfer_type = 2'b01;
        src_module = 1; // For Peripheral 1
        dest_module = 0; // For Memory 0
        src_address = 5'd10; // Address 10 in Peripheral 1
        dest_address = 5'd15; // Address 15 in Memory 0
        words = 15;

        #10 DMA_req = 1'b1;

        $monitor("DMA_req = %b, drq = %b, hrq = %b, dack = %b, start_transfer = %b, transfer_done = %b, words to be transferred = %d, fifo count = %d",DMA_req,drq,hrq,dack,start_transfer,transfer_done,uut.words_to_be_transferred,uut.fifo_count);
        
        #10000 DMA_req = 1'b0;

        for(i=0; i<10; i=i+1)
            $display("Address = %d, Value = %d",dest_address+i,uut.memory0[dest_address+i]);

        $finish;
    end

endmodule

test.vcd
$date
	Mon May 06 14:49:15 2024
$end
$version
	Icarus Verilog
$end
$timescale
	1ps
$end
$scope module testbench $end
$var wire 1 ! transfer_done $end
$var wire 1 " start_transfer $end
$var wire 1 # hrq $end
$var wire 1 $ drq $end
$var wire 1 % dack $end
$var parameter 32 & CLK_PERIOD $end
$var reg 1 ' DMA_req $end
$var reg 1 ( clk $end
$var reg 5 ) dest_address [4:0] $end
$var reg 3 * dest_module [2:0] $end
$var reg 1 + rst $end
$var reg 5 , src_address [4:0] $end
$var reg 3 - src_module [2:0] $end
$var reg 2 . transfer_type [1:0] $end
$var reg 5 / words [4:0] $end
$var integer 32 0 i [31:0] $end
$scope module cpu $end
$var wire 1 ' DMA_req $end
$var wire 1 ( clk $end
$var wire 1 + rst $end
$var wire 1 ! transfer_done $end
$var wire 1 # hrq $end
$var wire 1 % dack $end
$var parameter 2 1 HOLD $end
$var parameter 2 2 HOLD_REQ $end
$var parameter 2 3 NORMAL $end
$var reg 1 $ drq $end
$var reg 1 " start_transfer $end
$var reg 2 4 state [1:0] $end
$upscope $end
$scope module uut $end
$var wire 1 ( clk $end
$var wire 5 5 dest_address [4:0] $end
$var wire 3 6 dest_module [2:0] $end
$var wire 1 $ drq $end
$var wire 1 + rst $end
$var wire 5 7 src_address [4:0] $end
$var wire 3 8 src_module [2:0] $end
$var wire 1 " start_transfer $end
$var wire 2 9 transfer_type [1:0] $end
$var wire 5 : words [4:0] $end
$var parameter 3 ; DELAY $end
$var parameter 32 < DELAY_CYCLES $end
$var parameter 3 = DMA_REQ $end
$var parameter 3 > DONE $end
$var parameter 32 ? FIFO_DEPTH $end
$var parameter 3 @ IDLE $end
$var parameter 3 A READ $end
$var parameter 3 B TRANSFER $end
$var reg 1 % dack $end
$var reg 2 C delay_cycles_counter [1:0] $end
$var reg 5 D dest_addr [4:0] $end
$var reg 4 E fifo_count [3:0] $end
$var reg 4 F fifo_rd_ptr [3:0] $end
$var reg 4 G fifo_wr_ptr [3:0] $end
$var reg 1 # hrq $end
$var reg 5 H src_addr [4:0] $end
$var reg 3 I state [2:0] $end
$var reg 1 ! transfer_done $end
$var reg 5 J words_to_be_transferred [4:0] $end
$upscope $end
$upscope $end
$enddefinitions $end
$comment Show the parameter values. $end
$dumpall
b11 B
b10 A
b1 @
b1000 ?
b101 >
b0 =
b10 <
b100 ;
b0 3
b1 2
b10 1
b1010 &
$end
#0
$dumpvars
bx J
b0 I
b0 H
b0 G
b0 F
b0 E
b0 D
b0 C
bx :
bx 9
bx 8
bx 7
bx 6
bx 5
bx 4
b1111 0
bx /
bx .
bx -
bx ,
1+
bx *
bx )
0(
x'
x%
x$
x#
x"
0!
$end
#10000
b0 J
b0 4
0"
0$
1(
#20000
0(
b1111 /
b1111 :
b1111 )
b1111 5
b1010 ,
b1010 7
b0 *
b0 6
b1 -
b1 8
b1 .
b1 9
0+
#30000
b1 4
1$
0#
1(
1'
#40000
0(
#50000
b1 I
1#
1(
#60000
0(
#70000
b10 4
1"
0%
1(
#80000
0(
#90000
b10 I
b1111 J
b1111 D
b1010 H
1%
1(
#100000
0(
#110000
b11 I
b1 E
b1 G
1(
#120000
0(
#130000
b100 I
b1110 J
b10000 D
b1011 H
b0 E
b1 F
1(
#140000
0(
#150000
b1 C
1(
#160000
0(
#170000
b10 C
1(
#180000
0(
#190000
b10 I
b0 C
1(
#200000
0(
#210000
b11 I
b1 E
b10 G
1(
#220000
0(
#230000
b100 I
b1101 J
b10001 D
b1100 H
b0 E
b10 F
1(
#240000
0(
#250000
b1 C
1(
#260000
0(
#270000
b10 C
1(
#280000
0(
#290000
b10 I
b0 C
1(
#300000
0(
#310000
b11 I
b1 E
b11 G
1(
#320000
0(
#330000
b100 I
b1100 J
b10010 D
b1101 H
b0 E
b11 F
1(
#340000
0(
#350000
b1 C
1(
#360000
0(
#370000
b10 C
1(
#380000
0(
#390000
b10 I
b0 C
1(
#400000
0(
#410000
b11 I
b1 E
b100 G
1(
#420000
0(
#430000
b100 I
b1011 J
b10011 D
b1110 H
b0 E
b100 F
1(
#440000
0(
#450000
b1 C
1(
#460000
0(
#470000
b10 C
1(
#480000
0(
#490000
b10 I
b0 C
1(
#500000
0(
#510000
b11 I
b1 E
b101 G
1(
#520000
0(
#530000
b100 I
b1010 J
b10100 D
b1111 H
b0 E
b101 F
1(
#540000
0(
#550000
b1 C
1(
#560000
0(
#570000
b10 C
1(
#580000
0(
#590000
b10 I
b0 C
1(
#600000
0(
#610000
b11 I
b1 E
b110 G
1(
#620000
0(
#630000
b100 I
b1001 J
b10101 D
b10000 H
b0 E
b110 F
1(
#640000
0(
#650000
b1 C
1(
#660000
0(
#670000
b10 C
1(
#680000
0(
#690000
b10 I
b0 C
1(
#700000
0(
#710000
b11 I
b1 E
b111 G
1(
#720000
0(
#730000
b100 I
b1000 J
b10110 D
b10001 H
b0 E
b111 F
1(
#740000
0(
#750000
b1 C
1(
#760000
0(
#770000
b10 C
1(
#780000
0(
#790000
b10 I
b0 C
1(
#800000
0(
#810000
b11 I
b1 E
b0 G
1(
#820000
0(
#830000
b100 I
b111 J
b10111 D
b10010 H
b0 E
b0 F
1(
#840000
0(
#850000
b1 C
1(
#860000
0(
#870000
b10 C
1(
#880000
0(
#890000
b10 I
b0 C
1(
#900000
0(
#910000
b11 I
b1 E
b1 G
1(
#920000
0(
#930000
b100 I
b110 J
b11000 D
b10011 H
b0 E
b1 F
1(
#940000
0(
#950000
b1 C
1(
#960000
0(
#970000
b10 C
1(
#980000
0(
#990000
b10 I
b0 C
1(
#1000000
0(
#1010000
b11 I
b1 E
b10 G
1(
#1020000
0(
#1030000
b100 I
b101 J
b11001 D
b10100 H
b0 E
b10 F
1(
#1040000
0(
#1050000
b1 C
1(
#1060000
0(
#1070000
b10 C
1(
#1080000
0(
#1090000
b10 I
b0 C
1(
#1100000
0(
#1110000
b11 I
b1 E
b11 G
1(
#1120000
0(
#1130000
b100 I
b100 J
b11010 D
b10101 H
b0 E
b11 F
1(
#1140000
0(
#1150000
b1 C
1(
#1160000
0(
#1170000
b10 C
1(
#1180000
0(
#1190000
b10 I
b0 C
1(
#1200000
0(
#1210000
b11 I
b1 E
b100 G
1(
#1220000
0(
#1230000
b100 I
b11 J
b11011 D
b10110 H
b0 E
b100 F
1(
#1240000
0(
#1250000
b1 C
1(
#1260000
0(
#1270000
b10 C
1(
#1280000
0(
#1290000
b10 I
b0 C
1(
#1300000
0(
#1310000
b11 I
b1 E
b101 G
1(
#1320000
0(
#1330000
b100 I
b10 J
b11100 D
b10111 H
b0 E
b101 F
1(
#1340000
0(
#1350000
b1 C
1(
#1360000
0(
#1370000
b10 C
1(
#1380000
0(
#1390000
b10 I
b0 C
1(
#1400000
0(
#1410000
b11 I
b1 E
b110 G
1(
#1420000
0(
#1430000
b100 I
b1 J
b11101 D
b11000 H
b0 E
b110 F
1(
#1440000
0(
#1450000
b1 C
1(
#1460000
0(
#1470000
b10 C
1(
#1480000
0(
#1490000
b10 I
b0 C
1(
#1500000
0(
#1510000
b11 I
b1 E
b111 G
1(
#1520000
0(
#1530000
b100 I
b0 J
b11110 D
b11001 H
b0 E
b111 F
1(
#1540000
0(
#1550000
b1 C
1(
#1560000
0(
#1570000
b10 C
1(
#1580000
0(
#1590000
b101 I
b0 C
1(
#1600000
0(
#1610000
1!
1(
#1620000
0(
#1630000
b0 4
1(
#1640000
0(
#1650000
0$
1(
